deye_controller/__init__.py
deye_controller/deye_reader.py
deye_controller/logger_scan.py
deye_controller/modbus/__init__.py
deye_controller/modbus/enums.py
deye_controller/modbus/protocol.py
deye_controller/modbus/three_phase.py
deye_controller/modbus/utils.py
deye_controller/sell_programmer.py
deye_controller/utils/__init__.py
deye_controller/utils/connection.py
deye_controller/utils/groups.py
deye_controller/utils/monkey_patch.py
deye_controller-0.2.3.dist-info/LICENSE
deye_controller-0.2.3.dist-info/METADATA
deye_controller-0.2.3.dist-info/WHEEL
deye_controller-0.2.3.dist-info/entry_points.txt
deye_controller-0.2.3.dist-info/RECORD
