Metadata-Version: 2.3
Name: deye-controller
Version: 0.2.3
Summary: MODBUS Controller for DEYE inverters
License: MIT
Keywords: deye,inverter,deye-intverter
Author: githubDante
Author-email: github@dantetk.org
Requires-Python: >=3.8
Classifier: Development Status :: 5 - Production/Stable
Classifier: Intended Audience :: Developers
Classifier: License :: OSI Approved :: MIT License
Classifier: Programming Language :: Python :: 3
Classifier: Programming Language :: Python :: 3.8
Classifier: Programming Language :: Python :: 3.9
Classifier: Programming Language :: Python :: 3.10
Classifier: Programming Language :: Python :: 3.11
Classifier: Programming Language :: Python :: 3.12
Classifier: Programming Language :: Python :: 3.13
Classifier: Topic :: Software Development :: Libraries
Requires-Dist: pysolarmanv5 (>=3.0.4)
Project-URL: Repository, https://github.com/githubDante/deye-controller
